{"docs_contribute_codegen.md":"7363f323","docs_guide_usage_philosophy.md":"f41a1e5d","docs_contribute_formatter.md":"6c0eca8a","docs_contribute_introduction.md":"d97875d1","docs_contribute_linter.md":"a6253614","docs_contribute_development.md":"97b5b777","docs_contribute_minifier.md":"f56de112","docs_contribute_prettier.md":"53e3c6d2","docs_contribute_resolver.md":"6120abed","docs_guide_philosophy.md":"d6f8a27b","docs_guide_introduction.md":"2747d034","docs_guide_usage_parser.md":"4af36931","docs_guide_usage_benchmarks.md":"6fc15f21","blog_index.md":"f5232aac","docs_guide_usage_linter.md":"196722fd","docs_guide_usage_resolver.md":"2da5f677","docs_learn_architecture_minifier.md":"79241213","blog_2023-11-08-announcing-oxlint.md":"5b9a0911","blog_2022-08-08-linter-research.md":"8e79ea2a","blog_2023-11-07-announcing-oxc.md":"430c0264","docs_learn_architecture_transformer.md":"758d115f","docs_contribute_performance.md":"a17b6f48","docs_learn_ecosystem.md":"cd56f90b","docs_contribute_parser.md":"3d0130a9","docs_contribute_vscode.md":"7a51a221","docs_guide_benchmarks.md":"123a9894","docs_learn_architecture_formatter.md":"e166a67b","docs_learn_ecmascript_spec.md":"36082e85","ja_docs_contribute_linter.md":"97fc96a0","ja_docs_contribute_parser.md":"bf5ea805","ja_docs_contribute_performance.md":"23222511","ja_docs_contribute_prettier.md":"4ef929cb","ja_docs_contribute_resolver.md":"db2b9988","ja_docs_contribute_showcase.md":"3c03804a","ja_docs_contribute_transformer.md":"dfbe039f","ja_docs_contribute_minifier.md":"762a489c","ja_blog_2022-02-10-js-tooling-research.md":"e56890c5","ja_blog_2022-08-08-linter-research.md":"28eb2141","docs_learn_ecmascript_grammar.md":"75a8b105","ja_blog_2023-11-07-announcing-oxc.md":"7a56701c","ja_blog_2023-11-08-announcing-oxlint.md":"25d5bad4","ja_blog_index.md":"d0c17859","docs_contribute_showcase.md":"2e574dce","ja_docs_contribute_codegen.md":"217a3528","docs_learn_architecture_linter.md":"31551aa7","docs_learn_references.md":"aea099b8","ja_docs_contribute_introduction.md":"e42f0c49","docs_contribute_transformer.md":"adfc99aa","ja_docs_contribute_development.md":"501a4b21","ja_docs_guide_introduction.md":"0543a4c0","blog_2022-02-10-js-tooling-research.md":"ba426d4f","ja_docs_guide_philosophy.md":"4074dc16","ja_docs_guide_usage_linter.md":"8234e1b5","ja_docs_guide_usage_benchmarks.md":"ca7521f8","ja_docs_guide_usage_parser.md":"a5a47cb3","ja_docs_learn_architecture_formatter.md":"15eb4369","docs_learn_architecture_introduction.md":"43ae2bf7","ja_docs_contribute_formatter.md":"150cd5e6","docs_learn_architecture_resolver.md":"ff4b330d","docs_learn_architecture_parser.md":"965e99d1","docs_learn_performance.md":"cdbfea20","ja_docs_guide_usage_resolver.md":"746d5dec","ja_docs_guide_usage_philosophy.md":"0b2890fc","ja_docs_contribute_vscode.md":"0d1b9fdf","ja_docs_learn_architecture_linter.md":"07703f52","index.md":"4f3bc078","ja_docs_learn_architecture_resolver.md":"31988f40","ja_docs_guide_benchmarks.md":"0be655ba","ja_docs_learn_architecture_introduction.md":"aa2563bb","ja_docs_learn_architecture_parser.md":"d14dc3f5","ja_docs_learn_ecmascript_spec.md":"1e27acb1","ja_docs_learn_architecture_minifier.md":"6069c158","ja_docs_learn_ecmascript_grammar.md":"e851f538","ja_docs_learn_references.md":"f9a28869","ja_docs_learn_ecosystem.md":"537775c8","ja_docs_learn_performance.md":"5d0b4f54","ja_index.md":"1de84f41","ja_docs_learn_architecture_transformer.md":"a212a662"}
